liteyukibot_plugin_nonebot-0.1.3.dist-info/METADATA
liteyukibot_plugin_nonebot-0.1.3.dist-info/WHEEL
liteyukibot_plugin_nonebot-0.1.3.dist-info/licenses/LICENSE
liteyukibot_plugin_nonebot/__init__.py
liteyukibot_plugin_nonebot/dev_reloader.py
liteyukibot_plugin_nonebot/nb_utils/adapter_manager/__init__.py
liteyukibot_plugin_nonebot/nb_utils/adapter_manager/onebot.py
liteyukibot_plugin_nonebot/nb_utils/adapter_manager/satori.py
liteyukibot_plugin_nonebot/nb_utils/driver_manager/__init__.py
liteyukibot_plugin_nonebot/nb_utils/driver_manager/auto_set_env.py
liteyukibot_plugin_nonebot/nb_utils/driver_manager/defines.py
liteyukibot_plugin_nonebot/nonebot_plugins/to_liteyuki.py
liteyukibot_plugin_nonebot-0.1.3.dist-info/RECORD
